hdiiofficial/__init__.py
hdiiofficial/cli.py
hdiiofficial/client.py
hdiiofficial/config.py
hdiiofficial/constants.py
hdiiofficial/logger.py
hdiiofficial/settings.py
hdiiofficial/database/sql.py
hdiiofficial/database/telegram_db.py
hdiiofficial/database/tiny_db.py
hdiiofficial/decorators/__init__.py
hdiiofficial/decorators/callback.py
hdiiofficial/decorators/command.py
hdiiofficial/decorators/inline.py
hdiiofficial/helpers/localization.py
hdiiofficial/helpers/patch.py
hdiiofficial/helpers/process.py
hdiiofficial/helpers/stickers.py
hdiiofficial/methods/__init__.py
hdiiofficial/methods/message.py
hdiiofficial/plugins/hdev.py
hdiiofficial/plugins/helpers.py
hdiiofficial/plugins/HDevStore/sg.py
hdiiofficial/plugins/addons/about.py
hdiiofficial/plugins/addons/bans.py
hdiiofficial/plugins/addons/broadcast.py
hdiiofficial/plugins/addons/buttons.py
hdiiofficial/plugins/addons/help.py
hdiiofficial/plugins/addons/id.py
hdiiofficial/plugins/addons/json.py
hdiiofficial/plugins/addons/must_join.py
hdiiofficial/plugins/addons/start.py
hdiiofficial/plugins/addons/stats.py
hdiiofficial/plugins/addons/sudo.py
hdiiofficial/plugins/models/bans.py
hdiiofficial/plugins/models/users.py
hdiiofficial-1.6.5.dist-info/LICENSE
hdiiofficial-1.6.5.dist-info/METADATA
hdiiofficial-1.6.5.dist-info/NOTICE
hdiiofficial-1.6.5.dist-info/WHEEL
hdiiofficial-1.6.5.dist-info/dependency_links.txt
hdiiofficial-1.6.5.dist-info/entry_points.txt
hdiiofficial-1.6.5.dist-info/top_level.txt
hdiiofficial-1.6.5.dist-info/RECORD
