Metadata-Version: 2.1
Name: hdiiofficial
Version: 1.6.5
Summary: An add-on extension to Pyrogram for absolute beginners
Home-page: https://github.com/hdiiofficial/HDevpy
Author: hdiiofficial
Author-email: sshdiiofficial@wuuvo.com
License: GPLv3+
Project-URL: Support, https://t.me/hdiiofficial
Project-URL: Community, https://t.me/FunFriendsReborn
Project-URL: Updates, https://t.me/hdiiofficial
Project-URL: Documentation, https://hdiiofficial.sytes.net/HDevpy
Keywords: telegram,bot,pyrogram,python,telegram-bot
Classifier: Development Status :: 5 - Production/Stable
Classifier: Intended Audience :: Developers
Classifier: Intended Audience :: Education
Classifier: Intended Audience :: Information Technology
Classifier: License :: OSI Approved :: GNU General Public License v3 or later (GPLv3+)
Classifier: Operating System :: OS Independent
Classifier: Programming Language :: Python
Classifier: Programming Language :: Python :: 3
Classifier: Programming Language :: Python :: 3.9
Classifier: Programming Language :: Python :: 3.10
Classifier: Programming Language :: Python :: 3.11
Classifier: Natural Language :: English
Classifier: Topic :: Communications :: Chat
Classifier: Topic :: Education :: Testing
Classifier: Topic :: Software Development :: Libraries
Classifier: Topic :: Software Development :: Libraries :: Python Modules
Requires-Python: >=3.9
License-File: LICENSE
License-File: NOTICE
Requires-Dist: APScheduler (==3.7.0)
Requires-Dist: Pillow
Requires-Dist: aiohttp
Requires-Dist: asyncio
Requires-Dist: bs4
Requires-Dist: gitpython
Requires-Dist: googlesearch-python (==1.0.1)
Requires-Dist: gpytranslate
Requires-Dist: gtts
Requires-Dist: heroku3
Requires-Dist: lottie
Requires-Dist: motor
Requires-Dist: prettytable
Requires-Dist: psycopg2-binary
Requires-Dist: pyyaml (>=6.0)
Requires-Dist: pymediainfo
Requires-Dist: pytgcalls (==3.0.0.dev22)
Requires-Dist: pyrogram
Requires-Dist: pytz (>=2021.3)
Requires-Dist: python-dotenv
Requires-Dist: requests
Requires-Dist: speedtest-cli (==2.1.3)
Requires-Dist: sqlalchemy (==1.3.23)
Requires-Dist: telegraph
Requires-Dist: tgcrypto
Requires-Dist: tracemoepy
Requires-Dist: opencv-python-headless
Requires-Dist: urllib3
Requires-Dist: uvloop
Requires-Dist: wget (==3.2)
Requires-Dist: youtube-search-python
